pyhassbian/__init__.py
pyhassbian-0.0.1.dist-info/METADATA
pyhassbian-0.0.1.dist-info/RECORD
pyhassbian-0.0.1.dist-info/WHEEL
pyhassbian-0.0.1.dist-info/top_level.txt
